<annotation>
	<folder>frc</folder>
	<filename>1.maxresdefault.jpg</filename>
	<path>/home/alexiev/dev/vision/object_detection/train_images/frc/1.maxresdefault.jpg</path>
	<source>
		<database>Unknown</database>
	</source>
	<size>
		<width>800</width>
		<height>600</height>
		<depth>3</depth>
	</size>
	<segmented>0</segmented>
	<object>
		<name>robot</name>
		<pose>Unspecified</pose>
		<truncated>0</truncated>
		<difficult>0</difficult>
		<bndbox>
			<xmin>328</xmin>
			<ymin>199</ymin>
			<xmax>500</xmax>
			<ymax>476</ymax>
		</bndbox>
	</object>
	<object>
		<name>robot</name>
		<pose>Unspecified</pose>
		<truncated>0</truncated>
		<difficult>0</difficult>
		<bndbox>
			<xmin>147</xmin>
			<ymin>291</ymin>
			<xmax>268</xmax>
			<ymax>346</ymax>
		</bndbox>
	</object>
</annotation>
