<annotation>
	<folder>frc</folder>
	<filename>19.FRC-Austin-Sun-8660-960x640.jpg</filename>
	<path>/home/alexiev/dev/vision/object_detection/train_images/frc/19.FRC-Austin-Sun-8660-960x640.jpg</path>
	<source>
		<database>Unknown</database>
	</source>
	<size>
		<width>800</width>
		<height>600</height>
		<depth>3</depth>
	</size>
	<segmented>0</segmented>
	<object>
		<name>robot</name>
		<pose>Unspecified</pose>
		<truncated>0</truncated>
		<difficult>0</difficult>
		<bndbox>
			<xmin>122</xmin>
			<ymin>52</ymin>
			<xmax>572</xmax>
			<ymax>574</ymax>
		</bndbox>
	</object>
	<object>
		<name>robot</name>
		<pose>Unspecified</pose>
		<truncated>0</truncated>
		<difficult>0</difficult>
		<bndbox>
			<xmin>96</xmin>
			<ymin>25</ymin>
			<xmax>393</xmax>
			<ymax>425</ymax>
		</bndbox>
	</object>
</annotation>
